python_miniproject/__init__.py
python_miniproject/main.py
CLI_Parser_miniproject-0.0.5.dist-info/LICENSE
CLI_Parser_miniproject-0.0.5.dist-info/METADATA
CLI_Parser_miniproject-0.0.5.dist-info/WHEEL
CLI_Parser_miniproject-0.0.5.dist-info/top_level.txt
CLI_Parser_miniproject-0.0.5.dist-info/RECORD
