Metadata-Version: 2.1
Name: CLI-Parser-miniproject
Version: 0.0.5
Summary: python module
Home-page: UNKNOWN
License: UNKNOWN
Platform: UNKNOWN
Classifier: Programming Language :: Python :: 3
Classifier: Operating System :: OS Independent
Requires-Dist: tqdm (==4.64.1)
